[
  {
    "name": "Part_1",
    "cx_px": 1331,
    "cy_px": 482,
    "color": "Blue",
    "diameter_mm": 55.16296625137329
  },
  {
    "name": "Part_2",
    "cx_px": 1439,
    "cy_px": 684,
    "color": "Blue",
    "diameter_mm": 50.163090229034424
  },
  {
    "name": "Part_3",
    "cx_px": 1552,
    "cy_px": 622,
    "color": "Blue",
    "diameter_mm": 52.708595991134644
  },
  {
    "name": "Part_4",
    "cx_px": 1446,
    "cy_px": 421,
    "color": "Green",
    "diameter_mm": 48.61292243003845
  },
  {
    "name": "Part_5",
    "cx_px": 1557,
    "cy_px": 492,
    "color": "Green",
    "diameter_mm": 48.57751727104187
  },
  {
    "name": "Part_6",
    "cx_px": 1326,
    "cy_px": 613,
    "color": "Red",
    "diameter_mm": 48.08591306209564
  }
]